<?xml version='1.0' encoding='ISO-8859-15'?>
<Finvoice Version='1.3'><SellerPartyDetails><SellerOrganisationName>Oriola Finland Oy</SellerOrganisationName><SellerOrganisationTaxCode>FI01122827</SellerOrganisationTaxCode><SellerPostalAddressDetails><SellerStreetName>Orionintie 5</SellerStreetName><SellerTownName>ESPOO</SellerTownName><SellerPostCodeIdentifier>02101</SellerPostCodeIdentifier><CountryCode>FI</CountryCode><CountryName>Finland</CountryName></SellerPostalAddressDetails></SellerPartyDetails><SellerContactPersonName>RFCUSER</SellerContactPersonName><SellerCommunicationDetails><SellerPhoneNumberIdentifier>+358 10 42999</SellerPhoneNumberIdentifier></SellerCommunicationDetails><SellerInformationDetails><SellerPhoneNumber>+358 10 42999</SellerPhoneNumber></SellerInformationDetails><InvoiceRecipientPartyDetails><InvoiceRecipientPartyIdentifier>60001677</InvoiceRecipientPartyIdentifier><InvoiceRecipientOrganisationName>Helsingin 17. Kaivopuiston apteekki</InvoiceRecipientOrganisationName><InvoiceRecipientPostalAddressDetails><InvoiceRecipientStreetName>Muuntotie 1</InvoiceRecipientStreetName><InvoiceRecipientTownName>VANTAA</InvoiceRecipientTownName><InvoiceRecipientPostCodeIdentifier>01510</InvoiceRecipientPostCodeIdentifier><CountryCode>FI</CountryCode><CountryName>Finland</CountryName></InvoiceRecipientPostalAddressDetails></InvoiceRecipientPartyDetails><BuyerPartyDetails><BuyerPartyIdentifier>60001677</BuyerPartyIdentifier><BuyerOrganisationName>Helsingin 17. Kaivopuiston apteekki</BuyerOrganisationName><BuyerPostalAddressDetails><BuyerStreetName>Muuntotie 1</BuyerStreetName><BuyerTownName>VANTAA</BuyerTownName><BuyerPostCodeIdentifier>01510</BuyerPostCodeIdentifier><CountryCode>FI</CountryCode><CountryName>Finland</CountryName></BuyerPostalAddressDetails></BuyerPartyDetails><DeliveryPartyDetails><DeliveryPartyIdentifier>0060001677</DeliveryPartyIdentifier><DeliveryOrganisationName>Helsingin 17. Kaivopuiston apteekki</DeliveryOrganisationName><DeliveryPostalAddressDetails><DeliveryStreetName>Muuntotie 1</DeliveryStreetName><DeliveryTownName>VANTAA</DeliveryTownName><DeliveryPostCodeIdentifier>01510</DeliveryPostCodeIdentifier><CountryCode>FI</CountryCode><CountryName>Finland</CountryName></DeliveryPostalAddressDetails></DeliveryPartyDetails><InvoiceDetails><ShipmentNumber>8010709017</ShipmentNumber><ShipmentDate>20260428</ShipmentDate><RouteId>F0101</RouteId><RouteTime>23:05:08</RouteTime><RouteDescription></RouteDescription><OrderNumber>0006624170</OrderNumber><InvoiceHandler>RFCUSER</InvoiceHandler><InvoiceHandlerPhone>0401631656</InvoiceHandlerPhone><CustomerReference>Order Broker</CustomerReference><CustomerOrder>27763</CustomerOrder><InsuranceFeeVatExcluded AmountCurrencyIdentifier=''>4,49</InsuranceFeeVatExcluded><InsuranceFeeVatIncluded AmountCurrencyIdentifier=''>5,63</InsuranceFeeVatIncluded><DeliveryFeeVariableVatExcluded AmountCurrencyIdentifier=''>9,06</DeliveryFeeVariableVatExcluded><DeliveryFeeVariableVatIncluded AmountCurrencyIdentifier=''>495,42</DeliveryFeeVariableVatIncluded><InvoiceTotalVatExcludedAmount AmountCurrencyIdentifier=''>3607,15</InvoiceTotalVatExcludedAmount><InvoiceTotalVatAmount AmountCurrencyIdentifier=''>4093,51</InvoiceTotalVatAmount><InvoiceTotalVatIncludedAmount AmountCurrencyIdentifier='EUR'>495,42</InvoiceTotalVatIncludedAmount></InvoiceDetails><InvoiceRow><PicklistNumber>8010709017</PicklistNumber><BoxlistNumber>264300256312719250</BoxlistNumber><Package><PackageNumber>264300256312719250</PackageNumber><PackageType>Bluetote All</PackageType></Package><ArticleIdentifier>10146094</ArticleIdentifier><VnrIdentifier>035591</VnrIdentifier><ArticleName>Moxalole Jauhe 100 Annospussia</ArticleName><DeliveredQuantity QuantityUnitCode='EA'>1</DeliveredQuantity><OrderedQuantity QuantityUnitCode='EA'>1</OrderedQuantity><ArticleBatcNumber>0624776</ArticleBatcNumber><BatcUseByDate Format='CCYYMMDD'>20280831</BatcUseByDate><UnitPriceAmount AmountCurrencyIdentifier='EUR'>35,67</UnitPriceAmount><UnitNetPriceAmount AmountCurrencyIdentifier='EUR'>35,80</UnitNetPriceAmount><RowVatExcludedAmount AmountCurrencyIdentifier='EUR'>35,80</RowVatExcludedAmount><RowVatIncludedAmount AmountCurrencyIdentifier='EUR'>40,64</RowVatIncludedAmount></InvoiceRow><InvoiceRow><PicklistNumber>8010709017</PicklistNumber><BoxlistNumber>264300256312719908</BoxlistNumber><Package><PackageNumber>264300256312719908</PackageNumber><PackageType>Box Outbound</PackageType></Package><ArticleIdentifier>10009789</ArticleIdentifier><VnrIdentifier>053452</VnrIdentifier><ArticleName>Pegorion 12g oral sol powd 20 20pss FI</ArticleName><DeliveredQuantity QuantityUnitCode='EA'>12</DeliveredQuantity><OrderedQuantity QuantityUnitCode='EA'>24</OrderedQuantity><ArticleBatcNumber>20626</ArticleBatcNumber><BatcUseByDate Format='CCYYMMDD'>20280930</BatcUseByDate><UnitPriceAmount AmountCurrencyIdentifier='EUR'>9,27</UnitPriceAmount><UnitNetPriceAmount AmountCurrencyIdentifier='EUR'>9,31</UnitNetPriceAmount><RowVatExcludedAmount AmountCurrencyIdentifier='EUR'>111,72</RowVatExcludedAmount><RowVatIncludedAmount AmountCurrencyIdentifier='EUR'>126,81</RowVatIncludedAmount></InvoiceRow><InvoiceRow><PicklistNumber>8010709017</PicklistNumber><BoxlistNumber>264300256312719939</BoxlistNumber><Package><PackageNumber>264300256312719939</PackageNumber><PackageType>Box Outbound</PackageType></Package><ArticleIdentifier>10009789</ArticleIdentifier><VnrIdentifier>053452</VnrIdentifier><ArticleName>Pegorion 12g oral sol powd 20 20pss FI</ArticleName><DeliveredQuantity QuantityUnitCode='EA'>12</DeliveredQuantity><OrderedQuantity QuantityUnitCode='EA'>24</OrderedQuantity><ArticleBatcNumber>20626</ArticleBatcNumber><BatcUseByDate Format='CCYYMMDD'>20280930</BatcUseByDate><UnitPriceAmount AmountCurrencyIdentifier='EUR'>9,27</UnitPriceAmount><UnitNetPriceAmount AmountCurrencyIdentifier='EUR'>9,31</UnitNetPriceAmount><RowVatExcludedAmount AmountCurrencyIdentifier='EUR'>111,72</RowVatExcludedAmount><RowVatIncludedAmount AmountCurrencyIdentifier='EUR'>126,81</RowVatIncludedAmount></InvoiceRow><InvoiceRow><PicklistNumber>8010709017</PicklistNumber><BoxlistNumber>264300256312729419</BoxlistNumber><Package><PackageNumber>264300256312729419</PackageNumber><PackageType>Bluetote All</PackageType></Package><ArticleIdentifier>10112068</ArticleIdentifier><VnrIdentifier>457028</VnrIdentifier><ArticleName>BETADINE 100 mg/ml Cutaneous sol 250 ml</ArticleName><DeliveredQuantity QuantityUnitCode='EA'>7</DeliveredQuantity><OrderedQuantity QuantityUnitCode='EA'>7</OrderedQuantity><ArticleBatcNumber>107675</ArticleBatcNumber><BatcUseByDate Format='CCYYMMDD'>20280930</BatcUseByDate><UnitPriceAmount AmountCurrencyIdentifier='EUR'>7,54</UnitPriceAmount><UnitNetPriceAmount AmountCurrencyIdentifier='EUR'>7,57</UnitNetPriceAmount><RowVatExcludedAmount AmountCurrencyIdentifier='EUR'>52,99</RowVatExcludedAmount><RowVatIncludedAmount AmountCurrencyIdentifier='EUR'>60,15</RowVatIncludedAmount></InvoiceRow><InvoiceRow><PicklistNumber>8010709017</PicklistNumber><BoxlistNumber>264300256312729419</BoxlistNumber><Package><PackageNumber>264300256312729419</PackageNumber><PackageType>Bluetote All</PackageType></Package><ArticleIdentifier>10112273</ArticleIdentifier><VnrIdentifier>529604</VnrIdentifier><ArticleName>Calcichew D3 Opti man 500mg25mcg tab 100</ArticleName><DeliveredQuantity QuantityUnitCode='EA'>20</DeliveredQuantity><OrderedQuantity QuantityUnitCode='EA'>20</OrderedQuantity><ArticleBatcNumber>12531545</ArticleBatcNumber><BatcUseByDate Format='CCYYMMDD'>20280831</BatcUseByDate><UnitPriceAmount AmountCurrencyIdentifier='EUR'>12,55</UnitPriceAmount><UnitNetPriceAmount AmountCurrencyIdentifier='EUR'>11,59</UnitNetPriceAmount><RowVatExcludedAmount AmountCurrencyIdentifier='EUR'>231,80</RowVatExcludedAmount><RowVatIncludedAmount AmountCurrencyIdentifier='EUR'>263,13</RowVatIncludedAmount></InvoiceRow><InvoiceRow><PicklistNumber>8010709017</PicklistNumber><BoxlistNumber>264300256312729419</BoxlistNumber><Package><PackageNumber>264300256312729419</PackageNumber><PackageType>Bluetote All</PackageType></Package><ArticleIdentifier>10148137</ArticleIdentifier><VnrIdentifier>426806</VnrIdentifier><ArticleName>Frontline 100 mg/ml vet kissa, 3x0,5 ml</ArticleName><DeliveredQuantity QuantityUnitCode='EA'>7</DeliveredQuantity><OrderedQuantity QuantityUnitCode='EA'>10</OrderedQuantity><ArticleBatcNumber>G52306B</ArticleBatcNumber><BatcUseByDate Format='CCYYMMDD'>20270930</BatcUseByDate><UnitPriceAmount AmountCurrencyIdentifier='EUR'>15,41</UnitPriceAmount><UnitNetPriceAmount AmountCurrencyIdentifier='EUR'>15,47</UnitNetPriceAmount><RowVatExcludedAmount AmountCurrencyIdentifier='EUR'>108,29</RowVatExcludedAmount><RowVatIncludedAmount AmountCurrencyIdentifier='EUR'>122,93</RowVatIncludedAmount></InvoiceRow><InvoiceRow><PicklistNumber>8010709017</PicklistNumber><BoxlistNumber>264300256312729419</BoxlistNumber><Package><PackageNumber>264300256312729419</PackageNumber><PackageType>Bluetote All</PackageType></Package><ArticleIdentifier>10148137</ArticleIdentifier><VnrIdentifier>426806</VnrIdentifier><ArticleName>Frontline 100 mg/ml vet kissa, 3x0,5 ml</ArticleName><DeliveredQuantity QuantityUnitCode='EA'>3</DeliveredQuantity><OrderedQuantity QuantityUnitCode='EA'>10</OrderedQuantity><ArticleBatcNumber>G52306B</ArticleBatcNumber><BatcUseByDate Format='CCYYMMDD'>20270930</BatcUseByDate><UnitPriceAmount AmountCurrencyIdentifier='EUR'>15,41</UnitPriceAmount><UnitNetPriceAmount AmountCurrencyIdentifier='EUR'>15,47</UnitNetPriceAmount><RowVatExcludedAmount AmountCurrencyIdentifier='EUR'>46,41</RowVatExcludedAmount><RowVatIncludedAmount AmountCurrencyIdentifier='EUR'>52,68</RowVatIncludedAmount></InvoiceRow><InvoiceRow><PicklistNumber>8010709017</PicklistNumber><BoxlistNumber>264300256312729426</BoxlistNumber><Package><PackageNumber>264300256312729426</PackageNumber><PackageType>Bluetote All</PackageType></Package><ArticleIdentifier>10159572</ArticleIdentifier><VnrIdentifier>168327</VnrIdentifier><ArticleName>ADTAB DOG 225MG X6BLCD NEZ1</ArticleName><DeliveredQuantity QuantityUnitCode='EA'>10</DeliveredQuantity><OrderedQuantity QuantityUnitCode='EA'>10</OrderedQuantity><ArticleBatcNumber>AL258108C</ArticleBatcNumber><BatcUseByDate Format='CCYYMMDD'>20280630</BatcUseByDate><UnitPriceAmount AmountCurrencyIdentifier='EUR'>43,20</UnitPriceAmount><UnitNetPriceAmount AmountCurrencyIdentifier='EUR'>43,36</UnitNetPriceAmount><RowVatExcludedAmount AmountCurrencyIdentifier='EUR'>433,60</RowVatExcludedAmount><RowVatIncludedAmount AmountCurrencyIdentifier='EUR'>492,21</RowVatIncludedAmount></InvoiceRow><InvoiceRow><PicklistNumber>8010709017</PicklistNumber><BoxlistNumber>264300256312729426</BoxlistNumber><Package><PackageNumber>264300256312729426</PackageNumber><PackageType>Bluetote All</PackageType></Package><ArticleIdentifier>10159569</ArticleIdentifier><VnrIdentifier>039063</VnrIdentifier><ArticleName>ADTAB DOG 900MG X6BLCD NEZ1</ArticleName><DeliveredQuantity QuantityUnitCode='EA'>20</DeliveredQuantity><OrderedQuantity QuantityUnitCode='EA'>20</OrderedQuantity><ArticleBatcNumber>AL260524A</ArticleBatcNumber><BatcUseByDate Format='CCYYMMDD'>20280731</BatcUseByDate><UnitPriceAmount AmountCurrencyIdentifier='EUR'>55,88</UnitPriceAmount><UnitNetPriceAmount AmountCurrencyIdentifier='EUR'>56,09</UnitNetPriceAmount><RowVatExcludedAmount AmountCurrencyIdentifier='EUR'>1121,80</RowVatExcludedAmount><RowVatIncludedAmount AmountCurrencyIdentifier='EUR'>1273,39</RowVatIncludedAmount></InvoiceRow><InvoiceRow><PicklistNumber>8010709017</PicklistNumber><BoxlistNumber>264300256312729426</BoxlistNumber><Package><PackageNumber>264300256312729426</PackageNumber><PackageType>Bluetote All</PackageType></Package><ArticleIdentifier>10146085</ArticleIdentifier><VnrIdentifier>395829</VnrIdentifier><ArticleName>Agiolax Rakeet 250 G</ArticleName><DeliveredQuantity QuantityUnitCode='EA'>1</DeliveredQuantity><OrderedQuantity QuantityUnitCode='EA'>1</OrderedQuantity><ArticleBatcNumber>8195775</ArticleBatcNumber><BatcUseByDate Format='CCYYMMDD'>20271130</BatcUseByDate><UnitPriceAmount AmountCurrencyIdentifier='EUR'>7,67</UnitPriceAmount><UnitNetPriceAmount AmountCurrencyIdentifier='EUR'>7,70</UnitNetPriceAmount><RowVatExcludedAmount AmountCurrencyIdentifier='EUR'>7,70</RowVatExcludedAmount><RowVatIncludedAmount AmountCurrencyIdentifier='EUR'>8,74</RowVatIncludedAmount></InvoiceRow><InvoiceRow><PicklistNumber>8010709017</PicklistNumber><BoxlistNumber>264300256312729426</BoxlistNumber><Package><PackageNumber>264300256312729426</PackageNumber><PackageType>Bluetote All</PackageType></Package><ArticleIdentifier>10110817</ArticleIdentifier><VnrIdentifier>425288</VnrIdentifier><ArticleName>Duraphat 5 mg/g hammastahna 3x51g</ArticleName><DeliveredQuantity QuantityUnitCode='EA'>8</DeliveredQuantity><OrderedQuantity QuantityUnitCode='EA'>8</OrderedQuantity><ArticleBatcNumber>5351FR63A2</ArticleBatcNumber><BatcUseByDate Format='CCYYMMDD'>20281130</BatcUseByDate><UnitPriceAmount AmountCurrencyIdentifier='EUR'>22,00</UnitPriceAmount><UnitNetPriceAmount AmountCurrencyIdentifier='EUR'>22,08</UnitNetPriceAmount><RowVatExcludedAmount AmountCurrencyIdentifier='EUR'>176,64</RowVatExcludedAmount><RowVatIncludedAmount AmountCurrencyIdentifier='EUR'>200,52</RowVatIncludedAmount></InvoiceRow><InvoiceRow><PicklistNumber>8010709017</PicklistNumber><BoxlistNumber>264300256312729426</BoxlistNumber><Package><PackageNumber>264300256312729426</PackageNumber><PackageType>Bluetote All</PackageType></Package><ArticleIdentifier>10116511</ArticleIdentifier><VnrIdentifier>559084</VnrIdentifier><ArticleName>Frontect paik.val.liuos 5-10 kg 3x1 ml</ArticleName><DeliveredQuantity QuantityUnitCode='EA'>5</DeliveredQuantity><OrderedQuantity QuantityUnitCode='EA'>5</OrderedQuantity><ArticleBatcNumber>H81752A</ArticleBatcNumber><BatcUseByDate Format='CCYYMMDD'>20281031</BatcUseByDate><UnitPriceAmount AmountCurrencyIdentifier='EUR'>21,79</UnitPriceAmount><UnitNetPriceAmount AmountCurrencyIdentifier='EUR'>21,87</UnitNetPriceAmount><RowVatExcludedAmount AmountCurrencyIdentifier='EUR'>109,35</RowVatExcludedAmount><RowVatIncludedAmount AmountCurrencyIdentifier='EUR'>124,13</RowVatIncludedAmount></InvoiceRow><InvoiceRow><PicklistNumber>8010709017</PicklistNumber><BoxlistNumber>264300256312729426</BoxlistNumber><Package><PackageNumber>264300256312729426</PackageNumber><PackageType>Bluetote All</PackageType></Package><ArticleIdentifier>10116509</ArticleIdentifier><VnrIdentifier>189073</VnrIdentifier><ArticleName>Frontect paik.val.liuos 20-40 kg 3x4 ml</ArticleName><DeliveredQuantity QuantityUnitCode='EA'>4</DeliveredQuantity><OrderedQuantity QuantityUnitCode='EA'>4</OrderedQuantity><ArticleBatcNumber>H10878A</ArticleBatcNumber><BatcUseByDate Format='CCYYMMDD'>20280131</BatcUseByDate><UnitPriceAmount AmountCurrencyIdentifier='EUR'>32,12</UnitPriceAmount><UnitNetPriceAmount AmountCurrencyIdentifier='EUR'>32,24</UnitNetPriceAmount><RowVatExcludedAmount AmountCurrencyIdentifier='EUR'>128,96</RowVatExcludedAmount><RowVatIncludedAmount AmountCurrencyIdentifier='EUR'>146,39</RowVatIncludedAmount></InvoiceRow><InvoiceRow><PicklistNumber>8010709017</PicklistNumber><BoxlistNumber>264300256312729426</BoxlistNumber><Package><PackageNumber>264300256312729426</PackageNumber><PackageType>Bluetote All</PackageType></Package><ArticleIdentifier>10110495</ArticleIdentifier><VnrIdentifier>041140</VnrIdentifier><ArticleName>FORXIGA TAB 10MG BL 7X14 EA FI+</ArticleName><DeliveredQuantity QuantityUnitCode='EA'>2</DeliveredQuantity><OrderedQuantity QuantityUnitCode='EA'>4</OrderedQuantity><ArticleBatcNumber>TETR</ArticleBatcNumber><BatcUseByDate Format='CCYYMMDD'>20281231</BatcUseByDate><UnitPriceAmount AmountCurrencyIdentifier='EUR'>106,64</UnitPriceAmount><UnitNetPriceAmount AmountCurrencyIdentifier='EUR'>107,04</UnitNetPriceAmount><RowVatExcludedAmount AmountCurrencyIdentifier='EUR'>214,08</RowVatExcludedAmount><RowVatIncludedAmount AmountCurrencyIdentifier='EUR'>243,02</RowVatIncludedAmount></InvoiceRow><InvoiceRow><PicklistNumber>8010709017</PicklistNumber><BoxlistNumber>264300256312729433</BoxlistNumber><Package><PackageNumber>264300256312729433</PackageNumber><PackageType>Bluetote All</PackageType></Package><ArticleIdentifier>10002905</ArticleIdentifier><VnrIdentifier>590822</VnrIdentifier><ArticleName>Precosa 250mg kapseli OTC 20kpl</ArticleName><DeliveredQuantity QuantityUnitCode='EA'>9</DeliveredQuantity><OrderedQuantity QuantityUnitCode='EA'>9</OrderedQuantity><ArticleBatcNumber>2022</ArticleBatcNumber><BatcUseByDate Format='CCYYMMDD'>20280930</BatcUseByDate><UnitPriceAmount AmountCurrencyIdentifier='EUR'>8,26</UnitPriceAmount><UnitNetPriceAmount AmountCurrencyIdentifier='EUR'>8,29</UnitNetPriceAmount><RowVatExcludedAmount AmountCurrencyIdentifier='EUR'>74,61</RowVatExcludedAmount><RowVatIncludedAmount AmountCurrencyIdentifier='EUR'>84,69</RowVatIncludedAmount></InvoiceRow><InvoiceRow><PicklistNumber>8010709017</PicklistNumber><BoxlistNumber>264300256312729433</BoxlistNumber><Package><PackageNumber>264300256312729433</PackageNumber><PackageType>Bluetote All</PackageType></Package><ArticleIdentifier>10110495</ArticleIdentifier><VnrIdentifier>041140</VnrIdentifier><ArticleName>FORXIGA TAB 10MG BL 7X14 EA FI+</ArticleName><DeliveredQuantity QuantityUnitCode='EA'>2</DeliveredQuantity><OrderedQuantity QuantityUnitCode='EA'>4</OrderedQuantity><ArticleBatcNumber>TETR</ArticleBatcNumber><BatcUseByDate Format='CCYYMMDD'>20281231</BatcUseByDate><UnitPriceAmount AmountCurrencyIdentifier='EUR'>106,64</UnitPriceAmount><UnitNetPriceAmount AmountCurrencyIdentifier='EUR'>107,04</UnitNetPriceAmount><RowVatExcludedAmount AmountCurrencyIdentifier='EUR'>214,08</RowVatExcludedAmount><RowVatIncludedAmount AmountCurrencyIdentifier='EUR'>243,02</RowVatIncludedAmount></InvoiceRow><InvoiceRow><PicklistNumber>8010709017</PicklistNumber><BoxlistNumber>264300256312732303</BoxlistNumber><Package><PackageNumber>264300256312732303</PackageNumber><PackageType>Bluetote All</PackageType></Package><ArticleIdentifier>10003970</ArticleIdentifier><VnrIdentifier>117622</VnrIdentifier><ArticleName>Burana 200mg tabl 30kpl</ArticleName><DeliveredQuantity QuantityUnitCode='EA'>10</DeliveredQuantity><OrderedQuantity QuantityUnitCode='EA'>10</OrderedQuantity><ArticleBatcNumber>3051933</ArticleBatcNumber><BatcUseByDate Format='CCYYMMDD'>20280831</BatcUseByDate><UnitPriceAmount AmountCurrencyIdentifier='EUR'>3,18</UnitPriceAmount><UnitNetPriceAmount AmountCurrencyIdentifier='EUR'>3,19</UnitNetPriceAmount><RowVatExcludedAmount AmountCurrencyIdentifier='EUR'>31,90</RowVatExcludedAmount><RowVatIncludedAmount AmountCurrencyIdentifier='EUR'>36,21</RowVatIncludedAmount></InvoiceRow><InvoiceRow><PicklistNumber>8010709017</PicklistNumber><BoxlistNumber>264300256312732303</BoxlistNumber><Package><PackageNumber>264300256312732303</PackageNumber><PackageType>Bluetote All</PackageType></Package><ArticleIdentifier>10095721</ArticleIdentifier><VnrIdentifier>373451</VnrIdentifier><ArticleName>ELETRIPTAN ORION 40MG FCTABL 18 FI</ArticleName><DeliveredQuantity QuantityUnitCode='EA'>1</DeliveredQuantity><OrderedQuantity QuantityUnitCode='EA'>1</OrderedQuantity><ArticleBatcNumber>EL4025011A</ArticleBatcNumber><BatcUseByDate Format='CCYYMMDD'>20280930</BatcUseByDate><UnitPriceAmount AmountCurrencyIdentifier='EUR'>10,24</UnitPriceAmount><UnitNetPriceAmount AmountCurrencyIdentifier='EUR'>10,28</UnitNetPriceAmount><RowVatExcludedAmount AmountCurrencyIdentifier='EUR'>10,28</RowVatExcludedAmount><RowVatIncludedAmount AmountCurrencyIdentifier='EUR'>11,67</RowVatIncludedAmount></InvoiceRow><InvoiceRow><PicklistNumber>8010709017</PicklistNumber><BoxlistNumber>264300256312732303</BoxlistNumber><Package><PackageNumber>264300256312732303</PackageNumber><PackageType>Bluetote All</PackageType></Package><ArticleIdentifier>10000060</ArticleIdentifier><VnrIdentifier>486571</VnrIdentifier><ArticleName>Marevan 3mg tabl 100kpl</ArticleName><DeliveredQuantity QuantityUnitCode='EA'>1</DeliveredQuantity><OrderedQuantity QuantityUnitCode='EA'>1</OrderedQuantity><ArticleBatcNumber>3066747</ArticleBatcNumber><BatcUseByDate Format='CCYYMMDD'>20281231</BatcUseByDate><UnitPriceAmount AmountCurrencyIdentifier='EUR'>5,29</UnitPriceAmount><UnitNetPriceAmount AmountCurrencyIdentifier='EUR'>5,31</UnitNetPriceAmount><RowVatExcludedAmount AmountCurrencyIdentifier='EUR'>5,31</RowVatExcludedAmount><RowVatIncludedAmount AmountCurrencyIdentifier='EUR'>6,03</RowVatIncludedAmount></InvoiceRow><InvoiceRow><PicklistNumber>8010709017</PicklistNumber><BoxlistNumber>264300256312732303</BoxlistNumber><Package><PackageNumber>264300256312732303</PackageNumber><PackageType>Bluetote All</PackageType></Package><ArticleIdentifier>10112353</ArticleIdentifier><VnrIdentifier>067710</VnrIdentifier><ArticleName>Prednisolon 20 mg tabl 30</ArticleName><DeliveredQuantity QuantityUnitCode='EA'>10</DeliveredQuantity><OrderedQuantity QuantityUnitCode='EA'>10</OrderedQuantity><ArticleBatcNumber>107210</ArticleBatcNumber><BatcUseByDate Format='CCYYMMDD'>20280531</BatcUseByDate><UnitPriceAmount AmountCurrencyIdentifier='EUR'>3,47</UnitPriceAmount><UnitNetPriceAmount AmountCurrencyIdentifier='EUR'>3,48</UnitNetPriceAmount><RowVatExcludedAmount AmountCurrencyIdentifier='EUR'>34,80</RowVatExcludedAmount><RowVatIncludedAmount AmountCurrencyIdentifier='EUR'>39,51</RowVatIncludedAmount></InvoiceRow><InvoiceRow><PicklistNumber>8010709017</PicklistNumber><BoxlistNumber>264300256312732303</BoxlistNumber><Package><PackageNumber>264300256312732303</PackageNumber><PackageType>Bluetote All</PackageType></Package><ArticleIdentifier>10141745</ArticleIdentifier><VnrIdentifier>394644</VnrIdentifier><ArticleName>SALMETEROL/FLUTICASON ORION 25/250mcg120</ArticleName><DeliveredQuantity QuantityUnitCode='EA'>5</DeliveredQuantity><OrderedQuantity QuantityUnitCode='EA'>5</OrderedQuantity><ArticleBatcNumber>4GB1678S1</ArticleBatcNumber><BatcUseByDate Format='CCYYMMDD'>20260831</BatcUseByDate><UnitPriceAmount AmountCurrencyIdentifier='EUR'>12,00</UnitPriceAmount><UnitNetPriceAmount AmountCurrencyIdentifier='EUR'>12,05</UnitNetPriceAmount><RowVatExcludedAmount AmountCurrencyIdentifier='EUR'>60,25</RowVatExcludedAmount><RowVatIncludedAmount AmountCurrencyIdentifier='EUR'>68,39</RowVatIncludedAmount></InvoiceRow><InvoiceRow><PicklistNumber>8010709017</PicklistNumber><BoxlistNumber>264300256312732303</BoxlistNumber><Package><PackageNumber>264300256312732303</PackageNumber><PackageType>Bluetote All</PackageType></Package><ArticleIdentifier>10000522</ArticleIdentifier><VnrIdentifier>176941</VnrIdentifier><ArticleName>Solomet 40mg/ml c.bupivac.depotinj. 2ml</ArticleName><DeliveredQuantity QuantityUnitCode='EA'>6</DeliveredQuantity><OrderedQuantity QuantityUnitCode='EA'>6</OrderedQuantity><ArticleBatcNumber>3057648</ArticleBatcNumber><BatcUseByDate Format='CCYYMMDD'>20281130</BatcUseByDate><UnitPriceAmount AmountCurrencyIdentifier='EUR'>9,36</UnitPriceAmount><UnitNetPriceAmount AmountCurrencyIdentifier='EUR'>9,40</UnitNetPriceAmount><RowVatExcludedAmount AmountCurrencyIdentifier='EUR'>56,40</RowVatExcludedAmount><RowVatIncludedAmount AmountCurrencyIdentifier='EUR'>64,02</RowVatIncludedAmount></InvoiceRow><InvoiceRow><PicklistNumber>8010709017</PicklistNumber><BoxlistNumber>264300256312732303</BoxlistNumber><Package><PackageNumber>264300256312732303</PackageNumber><PackageType>Bluetote All</PackageType></Package><ArticleIdentifier>10085445</ArticleIdentifier><VnrIdentifier>578345</VnrIdentifier><ArticleName>TADALAFIL ORION 20 MG FC TABLET 12 FISED</ArticleName><DeliveredQuantity QuantityUnitCode='EA'>14</DeliveredQuantity><OrderedQuantity QuantityUnitCode='EA'>20</OrderedQuantity><ArticleBatcNumber>TGSD25018A</ArticleBatcNumber><BatcUseByDate Format='CCYYMMDD'>20290630</BatcUseByDate><UnitPriceAmount AmountCurrencyIdentifier='EUR'>3,31</UnitPriceAmount><UnitNetPriceAmount AmountCurrencyIdentifier='EUR'>3,32</UnitNetPriceAmount><RowVatExcludedAmount AmountCurrencyIdentifier='EUR'>46,48</RowVatExcludedAmount><RowVatIncludedAmount AmountCurrencyIdentifier='EUR'>52,77</RowVatIncludedAmount></InvoiceRow><InvoiceRow><PicklistNumber>8010709017</PicklistNumber><BoxlistNumber>264300256312732310</BoxlistNumber><Package><PackageNumber>264300256312732310</PackageNumber><PackageType>Bluetote All</PackageType></Package><ArticleIdentifier>10007348</ArticleIdentifier><VnrIdentifier>486276</VnrIdentifier><ArticleName>Ketipinor 100mg tabl JAR 100kpl</ArticleName><DeliveredQuantity QuantityUnitCode='EA'>3</DeliveredQuantity><OrderedQuantity QuantityUnitCode='EA'>3</OrderedQuantity><ArticleBatcNumber>3058267</ArticleBatcNumber><BatcUseByDate Format='CCYYMMDD'>20281130</BatcUseByDate><UnitPriceAmount AmountCurrencyIdentifier='EUR'>24,95</UnitPriceAmount><UnitNetPriceAmount AmountCurrencyIdentifier='EUR'>25,04</UnitNetPriceAmount><RowVatExcludedAmount AmountCurrencyIdentifier='EUR'>75,12</RowVatExcludedAmount><RowVatIncludedAmount AmountCurrencyIdentifier='EUR'>85,27</RowVatIncludedAmount></InvoiceRow><InvoiceRow><PicklistNumber>8010709017</PicklistNumber><BoxlistNumber>264300256312732310</BoxlistNumber><Package><PackageNumber>264300256312732310</PackageNumber><PackageType>Bluetote All</PackageType></Package><ArticleIdentifier>10003445</ArticleIdentifier><VnrIdentifier>047534</VnrIdentifier><ArticleName>Losartan Orion 50mg tabl 98kpl</ArticleName><DeliveredQuantity QuantityUnitCode='EA'>5</DeliveredQuantity><OrderedQuantity QuantityUnitCode='EA'>5</OrderedQuantity><ArticleBatcNumber>BJU6M003D</ArticleBatcNumber><BatcUseByDate Format='CCYYMMDD'>20291031</BatcUseByDate><UnitPriceAmount AmountCurrencyIdentifier='EUR'>3,41</UnitPriceAmount><UnitNetPriceAmount AmountCurrencyIdentifier='EUR'>3,42</UnitNetPriceAmount><RowVatExcludedAmount AmountCurrencyIdentifier='EUR'>17,10</RowVatExcludedAmount><RowVatIncludedAmount AmountCurrencyIdentifier='EUR'>19,42</RowVatIncludedAmount></InvoiceRow><InvoiceRow><PicklistNumber>8010709017</PicklistNumber><BoxlistNumber>264300256312732310</BoxlistNumber><Package><PackageNumber>264300256312732310</PackageNumber><PackageType>Bluetote All</PackageType></Package><ArticleIdentifier>10109886</ArticleIdentifier><VnrIdentifier>453644</VnrIdentifier><ArticleName>Metforem 750 mg pr tablet JAR 100 FI</ArticleName><DeliveredQuantity QuantityUnitCode='EA'>4</DeliveredQuantity><OrderedQuantity QuantityUnitCode='EA'>4</OrderedQuantity><ArticleBatcNumber>3061159</ArticleBatcNumber><BatcUseByDate Format='CCYYMMDD'>20281231</BatcUseByDate><UnitPriceAmount AmountCurrencyIdentifier='EUR'>7,19</UnitPriceAmount><UnitNetPriceAmount AmountCurrencyIdentifier='EUR'>7,22</UnitNetPriceAmount><RowVatExcludedAmount AmountCurrencyIdentifier='EUR'>28,88</RowVatExcludedAmount><RowVatIncludedAmount AmountCurrencyIdentifier='EUR'>32,78</RowVatIncludedAmount></InvoiceRow><InvoiceRow><PicklistNumber>8010709017</PicklistNumber><BoxlistNumber>264300256312732310</BoxlistNumber><Package><PackageNumber>264300256312732310</PackageNumber><PackageType>Bluetote All</PackageType></Package><ArticleIdentifier>10136176</ArticleIdentifier><VnrIdentifier>141791</VnrIdentifier><ArticleName>Recreol 50mg/g voide 30g</ArticleName><DeliveredQuantity QuantityUnitCode='EA'>2</DeliveredQuantity><OrderedQuantity QuantityUnitCode='EA'>2</OrderedQuantity><ArticleBatcNumber>8880824</ArticleBatcNumber><BatcUseByDate Format='CCYYMMDD'>20260731</BatcUseByDate><UnitPriceAmount AmountCurrencyIdentifier='EUR'>3,25</UnitPriceAmount><UnitNetPriceAmount AmountCurrencyIdentifier='EUR'>3,27</UnitNetPriceAmount><RowVatExcludedAmount AmountCurrencyIdentifier='EUR'>6,54</RowVatExcludedAmount><RowVatIncludedAmount AmountCurrencyIdentifier='EUR'>7,42</RowVatIncludedAmount></InvoiceRow><InvoiceRow><PicklistNumber>8010709017</PicklistNumber><BoxlistNumber>264300256312732310</BoxlistNumber><Package><PackageNumber>264300256312732310</PackageNumber><PackageType>Bluetote All</PackageType></Package><ArticleIdentifier>10100919</ArticleIdentifier><VnrIdentifier>810697</VnrIdentifier><ArticleName>Warticon 0,5% W/V solution 1x3ml</ArticleName><DeliveredQuantity QuantityUnitCode='EA'>1</DeliveredQuantity><OrderedQuantity QuantityUnitCode='EA'>1</OrderedQuantity><ArticleBatcNumber>W1B03</ArticleBatcNumber><BatcUseByDate Format='CCYYMMDD'>20280331</BatcUseByDate><UnitPriceAmount AmountCurrencyIdentifier='EUR'>34,50</UnitPriceAmount><UnitNetPriceAmount AmountCurrencyIdentifier='EUR'>34,63</UnitNetPriceAmount><RowVatExcludedAmount AmountCurrencyIdentifier='EUR'>34,63</RowVatExcludedAmount><RowVatIncludedAmount AmountCurrencyIdentifier='EUR'>39,31</RowVatIncludedAmount></InvoiceRow><InvoiceRow><PicklistNumber>8010709017</PicklistNumber><BoxlistNumber>264300256312732310</BoxlistNumber><Package><PackageNumber>264300256312732310</PackageNumber><PackageType>Bluetote All</PackageType></Package><ArticleIdentifier>10085445</ArticleIdentifier><VnrIdentifier>578345</VnrIdentifier><ArticleName>TADALAFIL ORION 20 MG FC TABLET 12 FISED</ArticleName><DeliveredQuantity QuantityUnitCode='EA'>6</DeliveredQuantity><OrderedQuantity QuantityUnitCode='EA'>20</OrderedQuantity><ArticleBatcNumber>TGSD25018A</ArticleBatcNumber><BatcUseByDate Format='CCYYMMDD'>20290630</BatcUseByDate><UnitPriceAmount AmountCurrencyIdentifier='EUR'>3,31</UnitPriceAmount><UnitNetPriceAmount AmountCurrencyIdentifier='EUR'>3,32</UnitNetPriceAmount><RowVatExcludedAmount AmountCurrencyIdentifier='EUR'>19,92</RowVatExcludedAmount><RowVatIncludedAmount AmountCurrencyIdentifier='EUR'>22,61</RowVatIncludedAmount></InvoiceRow></Finvoice>